MANIFEST.in
README.txt
setup.py
XStatic_fullcalendar.egg-info/PKG-INFO
XStatic_fullcalendar.egg-info/SOURCES.txt
XStatic_fullcalendar.egg-info/dependency_links.txt
XStatic_fullcalendar.egg-info/namespace_packages.txt
XStatic_fullcalendar.egg-info/not-zip-safe
XStatic_fullcalendar.egg-info/requires.txt
XStatic_fullcalendar.egg-info/top_level.txt
xstatic/__init__.py
xstatic/pkg/__init__.py
xstatic/pkg/fullcalendar/__init__.py
xstatic/pkg/fullcalendar/data/changelog.txt
xstatic/pkg/fullcalendar/data/fullcalendar.css
xstatic/pkg/fullcalendar/data/fullcalendar.js
xstatic/pkg/fullcalendar/data/fullcalendar.min.css
xstatic/pkg/fullcalendar/data/fullcalendar.min.js
xstatic/pkg/fullcalendar/data/fullcalendar.print.css
xstatic/pkg/fullcalendar/data/gcal.js
xstatic/pkg/fullcalendar/data/lang-all.js
xstatic/pkg/fullcalendar/data/license.txt
xstatic/pkg/fullcalendar/data/lang/ar-ma.js
xstatic/pkg/fullcalendar/data/lang/ar-sa.js
xstatic/pkg/fullcalendar/data/lang/ar.js
xstatic/pkg/fullcalendar/data/lang/bg.js
xstatic/pkg/fullcalendar/data/lang/ca.js
xstatic/pkg/fullcalendar/data/lang/cs.js
xstatic/pkg/fullcalendar/data/lang/da.js
xstatic/pkg/fullcalendar/data/lang/de-at.js
xstatic/pkg/fullcalendar/data/lang/de.js
xstatic/pkg/fullcalendar/data/lang/el.js
xstatic/pkg/fullcalendar/data/lang/en-au.js
xstatic/pkg/fullcalendar/data/lang/en-ca.js
xstatic/pkg/fullcalendar/data/lang/en-gb.js
xstatic/pkg/fullcalendar/data/lang/es.js
xstatic/pkg/fullcalendar/data/lang/fa.js
xstatic/pkg/fullcalendar/data/lang/fi.js
xstatic/pkg/fullcalendar/data/lang/fr-ca.js
xstatic/pkg/fullcalendar/data/lang/fr.js
xstatic/pkg/fullcalendar/data/lang/hi.js
xstatic/pkg/fullcalendar/data/lang/hr.js
xstatic/pkg/fullcalendar/data/lang/hu.js
xstatic/pkg/fullcalendar/data/lang/id.js
xstatic/pkg/fullcalendar/data/lang/is.js
xstatic/pkg/fullcalendar/data/lang/it.js
xstatic/pkg/fullcalendar/data/lang/ja.js
xstatic/pkg/fullcalendar/data/lang/ko.js
xstatic/pkg/fullcalendar/data/lang/lt.js
xstatic/pkg/fullcalendar/data/lang/lv.js
xstatic/pkg/fullcalendar/data/lang/nl.js
xstatic/pkg/fullcalendar/data/lang/pl.js
xstatic/pkg/fullcalendar/data/lang/pt-br.js
xstatic/pkg/fullcalendar/data/lang/pt.js
xstatic/pkg/fullcalendar/data/lang/ro.js
xstatic/pkg/fullcalendar/data/lang/ru.js
xstatic/pkg/fullcalendar/data/lang/sk.js
