Metadata-Version: 1.0
Name: XStatic-fullcalendar
Version: 2.2.2.1
Summary: fullcalendar 2.2.2 (XStatic packaging standard)
Home-page: http://arshaw.com/fullcalendar/
Author: Reimar Bauer
Author-email: rb.proj@googlemail.com
License: (same as fullcalendar)
Keywords: fullcalendar xstatic
Platform: any
